rm_rspace.py
rm_rspace-0.0.1.dist-info/LICENSE
rm_rspace-0.0.1.dist-info/METADATA
rm_rspace-0.0.1.dist-info/WHEEL
rm_rspace-0.0.1.dist-info/entry_points.txt
rm_rspace-0.0.1.dist-info/top_level.txt
rm_rspace-0.0.1.dist-info/RECORD
