Metadata-Version: 2.1
Name: rm-rspace
Version: 0.0.1
Summary: Remove trailing white spaces from a text file.
Home-page: https://github.com/masshash/rm_rspace
Author: Masashi Takahashi
Author-email: UNKNOWN
License: MIT
Platform: UNKNOWN
Classifier: Operating System :: OS Independent
Classifier: Environment :: Console
Classifier: License :: OSI Approved :: MIT License
Classifier: Natural Language :: Japanese
Classifier: Programming Language :: Python :: 2.7
Classifier: Programming Language :: Python :: 3
Classifier: Topic :: Utilities
